signing_mcp/__init__.py
signing_mcp/__main__.py
signing_mcp/server.py
signing_mcp/prompts/__init__.py
signing_mcp/prompts/message_workflow.py
signing_mcp/prompts/permit_workflow.py
signing_mcp/prompts/typed_data_workflow.py
signing_mcp/prompts/verification_workflow.py
signing_mcp/resources/__init__.py
signing_mcp/resources/eip191.py
signing_mcp/resources/eip712.py
signing_mcp/resources/signature_formats.py
signing_mcp/resources/typed_data_templates.py
signing_mcp/tools/__init__.py
signing_mcp/tools/hash_signing.py
signing_mcp/tools/message_signing.py
signing_mcp/tools/signature_utils.py
signing_mcp/tools/typed_data.py
signing_mcp_server-1.0.0.dist-info/METADATA
signing_mcp_server-1.0.0.dist-info/WHEEL
signing_mcp_server-1.0.0.dist-info/entry_points.txt
signing_mcp_server-1.0.0.dist-info/RECORD
