Metadata-Version: 2.4
Name: signing-mcp-server
Version: 1.0.0
Summary: MCP Server for Ethereum message signing and EIP-712 typed data
Project-URL: Homepage, https://github.com/nirholas/ethereum-wallet-toolkit
Project-URL: Repository, https://github.com/nirholas/ethereum-wallet-toolkit/tree/main/signing-mcp-server
Project-URL: Documentation, https://github.com/nirholas/ethereum-wallet-toolkit/blob/main/signing-mcp-server/README.md
Author-email: nirholas <nich@ethereum.tools>
License: MIT
Keywords: eip-191,eip-712,ethereum,mcp,message-signing,personal_sign,signing,typed-data
Classifier: Development Status :: 4 - Beta
Classifier: Intended Audience :: Developers
Classifier: License :: OSI Approved :: MIT License
Classifier: Programming Language :: Python :: 3
Classifier: Programming Language :: Python :: 3.11
Classifier: Programming Language :: Python :: 3.12
Classifier: Topic :: Security :: Cryptography
Classifier: Topic :: Software Development :: Libraries :: Python Modules
Requires-Python: >=3.11
Requires-Dist: eth-abi>=4.0.0
Requires-Dist: eth-account>=0.10.0
Requires-Dist: eth-utils>=2.0.0
Requires-Dist: mcp>=1.0.0
Provides-Extra: dev
Requires-Dist: black>=23.0.0; extra == 'dev'
Requires-Dist: mypy>=1.0.0; extra == 'dev'
Requires-Dist: pytest-asyncio>=0.21.0; extra == 'dev'
Requires-Dist: pytest>=7.0.0; extra == 'dev'
